signalfeed/__init__.py
signalfeed/exceptions.py
signalfeed-0.0.1.dist-info/LICENSE
signalfeed-0.0.1.dist-info/METADATA
signalfeed-0.0.1.dist-info/WHEEL
signalfeed-0.0.1.dist-info/top_level.txt
signalfeed-0.0.1.dist-info/RECORD
